procobserver/LICENSE
procobserver/README.MD
procobserver/__init__.py
procobserver/requirements.txt
procobserver/thirdparty.json
procobserver-0.10.dist-info/LICENSE.rst
procobserver-0.10.dist-info/METADATA
procobserver-0.10.dist-info/WHEEL
procobserver-0.10.dist-info/top_level.txt
procobserver-0.10.dist-info/RECORD
