Metadata-Version: 2.1
Name: procobserver
Version: 0.10
Summary: Uses psutil to observe/log processes during a certain time
Home-page: https://github.com/hansalemaos/procobserver
Author: Johannes Fischer
Author-email: <aulasparticularesdealemaosp@gmail.com>
License: MIT
Keywords: psutil,log,pid
Classifier: Development Status :: 4 - Beta
Classifier: Programming Language :: Python :: 3 :: Only
Classifier: Programming Language :: Python :: 3.9
Classifier: Topic :: Scientific/Engineering :: Visualization
Classifier: Topic :: Software Development :: Libraries :: Python Modules
Classifier: Topic :: Text Editors :: Text Processing
Classifier: Topic :: Text Processing :: General
Classifier: Topic :: Text Processing :: Indexing
Classifier: Topic :: Text Processing :: Filters
Classifier: Topic :: Utilities
License-File: LICENSE.rst
Requires-Dist: a-pandas-ex-dillpickle
Requires-Dist: deepcopyall
Requires-Dist: kthread-sleep
Requires-Dist: pandas
Requires-Dist: psutil
